pybrops/__init__.py
pybrops/breed/__init__.py
pybrops/breed/arch/BreedingEdge.py
pybrops/breed/arch/BreedingGraph.py
pybrops/breed/arch/BreedingNode.py
pybrops/breed/arch/BreedingProgram.py
pybrops/breed/arch/EmigrationOperator.py
pybrops/breed/arch/GermplasmBank.py
pybrops/breed/arch/ImmigrationOperator.py
pybrops/breed/arch/RecurrentSelectionBreedingProgram.py
pybrops/breed/arch/__init__.py
pybrops/breed/op/__init__.py
pybrops/breed/op/eval/EvaluationOperator.py
pybrops/breed/op/eval/__init__.py
pybrops/breed/op/init/InitializationOperator.py
pybrops/breed/op/init/__init__.py
pybrops/breed/op/log/Logbook.py
pybrops/breed/op/log/__init__.py
pybrops/breed/op/mate/MatingOperator.py
pybrops/breed/op/mate/__init__.py
pybrops/breed/op/psel/ParentSelectionOperator.py
pybrops/breed/op/psel/__init__.py
pybrops/breed/op/ssel/SurvivorSelectionOperator.py
pybrops/breed/op/ssel/__init__.py
pybrops/breed/prot/__init__.py
pybrops/breed/prot/bv/BreedingValueProtocol.py
pybrops/breed/prot/bv/MeanPhenotypicBreedingValue.py
pybrops/breed/prot/bv/TrueBreedingValue.py
pybrops/breed/prot/bv/__init__.py
pybrops/breed/prot/gt/DenseMaskedPhasedGenotyping.py
pybrops/breed/prot/gt/DenseMaskedUnphasedGenotyping.py
pybrops/breed/prot/gt/DenseUnphasedGenotyping.py
pybrops/breed/prot/gt/GenotypingProtocol.py
pybrops/breed/prot/gt/__init__.py
pybrops/breed/prot/mate/FourWayCross.py
pybrops/breed/prot/mate/FourWayDHCross.py
pybrops/breed/prot/mate/MatingProtocol.py
pybrops/breed/prot/mate/SelfCross.py
pybrops/breed/prot/mate/ThreeWayCross.py
pybrops/breed/prot/mate/ThreeWayDHCross.py
pybrops/breed/prot/mate/TwoWayCross.py
pybrops/breed/prot/mate/TwoWayDHCross.py
pybrops/breed/prot/mate/__init__.py
pybrops/breed/prot/mate/util.py
pybrops/breed/prot/pt/G_E_Phenotyping.py
pybrops/breed/prot/pt/PhenotypingProtocol.py
pybrops/breed/prot/pt/TruePhenotyping.py
pybrops/breed/prot/pt/__init__.py
pybrops/breed/prot/sel/BinaryMateSelectionProtocol.py
pybrops/breed/prot/sel/BinarySelectionProtocol.py
pybrops-1.0.3.dist-info/LICENSE
pybrops-1.0.3.dist-info/METADATA
pybrops-1.0.3.dist-info/WHEEL
pybrops-1.0.3.dist-info/top_level.txt
pybrops-1.0.3.dist-info/RECORD
