Metadata-Version: 2.1
Name: pybrops
Version: 1.0.3
Summary: Python package for breeding program numerical optimization and simulation
Home-page: https://github.com/rzshrote/pybrops
Author: Robert Z. Shrote
Author-email: shrotero@msu.edu
License: Apache License 2.0
Project-URL: Bug Tracker, https://github.com/rzshrote/pybrops/issues
Classifier: Programming Language :: Python :: 3
Classifier: License :: OSI Approved :: MIT License
Classifier: Operating System :: OS Independent
Requires-Python: >=3.6
License-File: LICENSE
Requires-Dist: numpy
Requires-Dist: pandas
Requires-Dist: scipy
Requires-Dist: matplotlib
Requires-Dist: pymoo
Requires-Dist: cyvcf2
Requires-Dist: h5py
Requires-Dist: DEAP
